pyFluxim/LL.py
pyFluxim/__init__.py
pyFluxim/flux.py
pyFluxim/utils.py
tests/__init__.py
tests/test_LL.py
tests/test_flux.py
tests/test_utils.py
pyFluxim-0.0.12.dist-info/METADATA
pyFluxim-0.0.12.dist-info/WHEEL
pyFluxim-0.0.12.dist-info/entry_points.txt
pyFluxim-0.0.12.dist-info/top_level.txt
pyFluxim-0.0.12.dist-info/RECORD
