Metadata-Version: 2.1
Name: pyFluxim
Version: 0.0.12
Summary: library to handle data generated by Fluxim's hardwares
Home-page: https://bitbucket.org/fluximag/pyfluxim
Author: Stefano Sem
Author-email: stefano.sem@fluxim.com
License: Apache 2.0
Keywords: fluxim litos lite phelos paios characterization suit
Platform: UNKNOWN
Classifier: Development Status :: 4 - Beta
Classifier: Topic :: Scientific/Engineering
Classifier: Programming Language :: Python :: 3
Classifier: Programming Language :: Python :: 3.4
Classifier: Programming Language :: Python :: 3.5
Classifier: Programming Language :: Python :: 3.6
Requires-Dist: numpy
Requires-Dist: matplotlib
Requires-Dist: h5py
